azure/functions/__init__.py
azure/functions/_abc.py
azure/functions/_cosmosdb.py
azure/functions/_durable_functions.py
azure/functions/_eventgrid.py
azure/functions/_eventhub.py
azure/functions/_http.py
azure/functions/_http_asgi.py
azure/functions/_http_wsgi.py
azure/functions/_kafka.py
azure/functions/_mysql.py
azure/functions/_queue.py
azure/functions/_servicebus.py
azure/functions/_sql.py
azure/functions/_utils.py
azure/functions/blob.py
azure/functions/cosmosdb.py
azure/functions/durable_functions.py
azure/functions/eventgrid.py
azure/functions/eventhub.py
azure/functions/http.py
azure/functions/kafka.py
azure/functions/meta.py
azure/functions/mysql.py
azure/functions/py.typed
azure/functions/queue.py
azure/functions/servicebus.py
azure/functions/sql.py
azure/functions/timer.py
azure/functions/warmup.py
azure/functions/_thirdparty/__init__.py
azure/functions/_thirdparty/typing_inspect.py
azure/functions/_thirdparty/werkzeug/__init__.py
azure/functions/_thirdparty/werkzeug/_compat.py
azure/functions/_thirdparty/werkzeug/_internal.py
azure/functions/_thirdparty/werkzeug/datastructures.py
azure/functions/_thirdparty/werkzeug/exceptions.py
azure/functions/_thirdparty/werkzeug/formparser.py
azure/functions/_thirdparty/werkzeug/http.py
azure/functions/_thirdparty/werkzeug/urls.py
azure/functions/_thirdparty/werkzeug/utils.py
azure/functions/_thirdparty/werkzeug/wsgi.py
azure/functions/decorators/__init__.py
azure/functions/decorators/blob.py
azure/functions/decorators/constants.py
azure/functions/decorators/core.py
azure/functions/decorators/cosmosdb.py
azure/functions/decorators/dapr.py
azure/functions/decorators/eventgrid.py
azure/functions/decorators/eventhub.py
azure/functions/decorators/function_app.py
azure/functions/decorators/function_name.py
azure/functions/decorators/generic.py
azure/functions/decorators/http.py
azure/functions/decorators/kafka.py
azure/functions/decorators/openai.py
azure/functions/decorators/queue.py
azure_functions-1.22.1.dist-info/LICENSE
azure_functions-1.22.1.dist-info/METADATA
azure_functions-1.22.1.dist-info/WHEEL
azure_functions-1.22.1.dist-info/top_level.txt
azure_functions-1.22.1.dist-info/RECORD
